lxcommondata/__init__.py
lxcommondata/apis.py
lxcommondata/client.py
lxcommondata/commondata_pb2.py
lxcommondata/commondata_pb2_grpc.py
lxcommondata/func.py
lxcommondata-0.0.8.dist-info/LICENSE
lxcommondata-0.0.8.dist-info/METADATA
lxcommondata-0.0.8.dist-info/WHEEL
lxcommondata-0.0.8.dist-info/top_level.txt
lxcommondata-0.0.8.dist-info/RECORD
