Metadata-Version: 2.1
Name: lxcommondata
Version: 0.0.8
Summary: lxcommondata
Home-page: https://github.com/pypa/sampleproject
Author: cuipengchong
Author-email: 1171014242@qq.com
License: UNKNOWN
Platform: UNKNOWN
Classifier: Programming Language :: Python :: 3
Classifier: License :: OSI Approved :: MIT License
Classifier: Operating System :: OS Independent
Requires-Python: >=3.7
